{"matching": [{"iscorrect": false, "visrep": "mx", "graph2": 41, "graph3": 121, "refgraph": 12, "answer": "A", "correctanswer": 121, "graph1": 51, "duration": "17366", "question": "1"}, {"iscorrect": false, "visrep": "cm", "graph2": 72, "graph3": 102, "refgraph": 7, "answer": "C", "correctanswer": 72, "graph1": 32, "duration": "24680", "question": "2"}, {"iscorrect": true, "visrep": "gt", "graph2": 6, "graph3": 8, "refgraph": 6, "answer": "B", "correctanswer": 6, "graph1": 13, "duration": "17483", "question": "3"}, {"iscorrect": false, "visrep": "mx", "graph2": 32, "graph3": 72, "refgraph": 7, "answer": "B", "correctanswer": 72, "graph1": 102, "duration": "15270", "question": "4"}, {"iscorrect": true, "visrep": "cm", "graph2": 91, "graph3": 22, "refgraph": 9, "answer": "B", "correctanswer": 91, "graph1": 52, "duration": "5345", "question": "5"}, {"iscorrect": true, "visrep": "gt", "graph2": 51, "graph3": 41, "refgraph": 12, "answer": "A", "correctanswer": 121, "graph1": 121, "duration": "14488", "question": "6"}, {"iscorrect": true, "visrep": "mx", "graph2": 52, "graph3": 91, "refgraph": 9, "answer": "C", "correctanswer": 91, "graph1": 22, "duration": "21941", "question": "7"}, {"iscorrect": true, "visrep": "cm", "graph2": 42, "graph3": 23, "refgraph": 4, "answer": "B", "correctanswer": 42, "graph1": 73, "duration": "3359", "question": "8"}, {"iscorrect": true, "visrep": "gt", "graph2": 102, "graph3": 32, "refgraph": 7, "answer": "A", "correctanswer": 72, "graph1": 72, "duration": "17969", "question": "9"}, {"iscorrect": false, "visrep": "mx", "graph2": 73, "graph3": 42, "refgraph": 4, "answer": "unsure", "correctanswer": 42, "graph1": 23, "duration": "9755", "question": "10"}, {"iscorrect": true, "visrep": "cm", "graph2": 43, "graph3": 81, "refgraph": 8, "answer": "C", "correctanswer": 81, "graph1": 61, "duration": "4703", "question": "11"}, {"iscorrect": true, "visrep": "gt", "graph2": 22, "graph3": 52, "refgraph": 9, "answer": "A", "correctanswer": 91, "graph1": 91, "duration": "4742", "question": "12"}, {"iscorrect": true, "visrep": "mx", "graph2": 61, "graph3": 43, "refgraph": 8, "answer": "A", "correctanswer": 81, "graph1": 81, "duration": "13095", "question": "13"}, {"iscorrect": true, "visrep": "cm", "graph2": 111, "graph3": 53, "refgraph": 10, "answer": "A", "correctanswer": 103, "graph1": 103, "duration": "5106", "question": "14"}, {"iscorrect": true, "visrep": "gt", "graph2": 23, "graph3": 73, "refgraph": 4, "answer": "A", "correctanswer": 42, "graph1": 42, "duration": "7262", "question": "15"}, {"iscorrect": false, "visrep": "mx", "graph2": 103, "graph3": 111, "refgraph": 10, "answer": "A", "correctanswer": 103, "graph1": 53, "duration": "7379", "question": "16"}, {"iscorrect": false, "visrep": "cm", "graph2": 11, "graph3": 13, "refgraph": 11, "answer": "unsure", "correctanswer": 11, "graph1": 71, "duration": "30161", "question": "17"}, {"iscorrect": true, "visrep": "gt", "graph2": 81, "graph3": 61, "refgraph": 8, "answer": "B", "correctanswer": 81, "graph1": 43, "duration": "3894", "question": "18"}, {"iscorrect": false, "visrep": "mx", "graph2": 71, "graph3": 11, "refgraph": 11, "answer": "B", "correctanswer": 11, "graph1": 13, "duration": "23341", "question": "19"}, {"iscorrect": true, "visrep": "cm", "graph2": 10, "graph3": 3, "refgraph": 2, "answer": "A", "correctanswer": 21, "graph1": 21, "duration": "20152", "question": "20"}, {"iscorrect": true, "visrep": "gt", "graph2": 53, "graph3": 103, "refgraph": 10, "answer": "C", "correctanswer": 103, "graph1": 111, "duration": "16496", "question": "21"}, {"iscorrect": false, "visrep": "mx", "graph2": 21, "graph3": 10, "refgraph": 2, "answer": "unsure", "correctanswer": 21, "graph1": 3, "duration": "29691", "question": "22"}, {"iscorrect": true, "visrep": "cm", "graph2": 101, "graph3": 7, "refgraph": 3, "answer": "A", "correctanswer": 31, "graph1": 31, "duration": "4488", "question": "23"}, {"iscorrect": true, "visrep": "gt", "graph2": 13, "graph3": 71, "refgraph": 11, "answer": "A", "correctanswer": 11, "graph1": 11, "duration": "5049", "question": "24"}, {"iscorrect": false, "visrep": "mx", "graph2": 31, "graph3": 101, "refgraph": 3, "answer": "unsure", "correctanswer": 31, "graph1": 7, "duration": "18616", "question": "25"}, {"iscorrect": false, "visrep": "cm", "graph2": 13, "graph3": 6, "refgraph": 6, "answer": "unsure", "correctanswer": 6, "graph1": 8, "duration": "21039", "question": "26"}, {"iscorrect": true, "visrep": "gt", "graph2": 3, "graph3": 21, "refgraph": 2, "answer": "C", "correctanswer": 21, "graph1": 10, "duration": "9684", "question": "27"}, {"iscorrect": false, "visrep": "mx", "graph2": 8, "graph3": 13, "refgraph": 6, "answer": "unsure", "correctanswer": 6, "graph1": 6, "duration": "20049", "question": "28"}, {"iscorrect": true, "visrep": "cm", "graph2": 121, "graph3": 51, "refgraph": 12, "answer": "B", "duration": "11885", "graph1": 41, "correctanswer": 121, "question": "29"}, {"iscorrect": true, "visrep": "gt", "graph2": 7, "question": "30", "refgraph": 3, "answer": "C", "duration": "6672", "graph1": 101, "correctanswer": 31, "graph3": 31}]}