{"dense": {"useridx": [2, 3, 4, 5, 6], "userorder": [0, 1], "usermode": "mx", "currentmode": "mx", "currentidx": [2, 3, 4, 5, 6], "currentorder": [0, 1]}, "usercount": 2, "connectivity": [{"currentgraph": [3, 4, 5, 6, 7], "currentmode": "mx", "usergraph": [3, 4, 5, 6, 7], "usermode": "mx"}, {"currentgraph": [4, 5, 6, 7, 3], "currentmode": "cn", "usergraph": [4, 5, 6, 7, 3], "usermode": "cn"}, {"currentgraph": [3, 4, 5, 1, 2], "currentmode": "mx", "usergraph": [3, 4, 5, 1, 2], "usermode": "mx"}], "mygraph": {"links": [{"target": {"py": 109.98091501061916, "y": 109.87644784420979, "x": 181.2500954500423, "index": 1, "weight": 4, "px": 181.1961762476734, "group": 1, "name": "B", "count": 4}, "source": {"py": 86.04501386415056, "y": 85.9439055032527, "x": 197.13123453913713, "index": 0, "weight": 1, "px": 197.05283896299326, "group": 1, "name": "A", "count": 1}, "value": 1, "index": 0, "distance": 1}, {"target": {"py": 115.8417026577427, "y": 115.7786456437307, "x": 161.75725315340017, "index": 2, "weight": 4, "px": 161.8305553067968, "group": 1, "name": "C", "count": 4}, "source": {"py": 109.98091501061916, "y": 109.87644784420979, "x": 181.2500954500423, "index": 1, "weight": 4, "px": 181.1961762476734, "group": 1, "name": "B", "count": 4}, "value": 1, "index": 1, "distance": 1}, {"target": {"py": 141.2212767674666, "y": 141.27620239855642, "x": 171.0878962019167, "index": 3, "weight": 5, "px": 171.08507976631708, "group": 1, "name": "D", "count": 5}, "source": {"py": 109.98091501061916, "y": 109.87644784420979, "x": 181.2500954500423, "index": 1, "weight": 4, "px": 181.1961762476734, "group": 1, "name": "B", "count": 4}, "value": 1, "index": 2, "distance": 1}, {"target": {"py": 126.31898383120767, "y": 126.33450915777004, "x": 184.7865793573908, "index": 4, "weight": 3, "px": 184.6837066614665, "group": 1, "name": "E", "count": 3}, "source": {"py": 109.98091501061916, "y": 109.87644784420979, "x": 181.2500954500423, "index": 1, "weight": 4, "px": 181.1961762476734, "group": 1, "name": "B", "count": 4}, "value": 1, "index": 3, "distance": 1}, {"target": {"py": 141.2212767674666, "y": 141.27620239855642, "x": 171.0878962019167, "index": 3, "weight": 5, "px": 171.08507976631708, "group": 1, "name": "D", "count": 5}, "source": {"py": 115.8417026577427, "y": 115.7786456437307, "x": 161.75725315340017, "index": 2, "weight": 4, "px": 161.8305553067968, "group": 1, "name": "C", "count": 4}, "value": 1, "index": 4, "distance": 1}, {"target": {"py": 126.31898383120767, "y": 126.33450915777004, "x": 184.7865793573908, "index": 4, "weight": 3, "px": 184.6837066614665, "group": 1, "name": "E", "count": 3}, "source": {"py": 115.8417026577427, "y": 115.7786456437307, "x": 161.75725315340017, "index": 2, "weight": 4, "px": 161.8305553067968, "group": 1, "name": "C", "count": 4}, "value": 1, "index": 5, "distance": 1}, {"target": {"py": 126.31898383120767, "y": 126.33450915777004, "x": 184.7865793573908, "index": 4, "weight": 3, "px": 184.6837066614665, "group": 1, "name": "E", "count": 3}, "source": {"py": 141.2212767674666, "y": 141.27620239855642, "x": 171.0878962019167, "index": 3, "weight": 5, "px": 171.08507976631708, "group": 1, "name": "D", "count": 5}, "value": 1, "index": 6, "distance": 1}, {"target": {"py": 148.0720222931251, "y": 148.09637522456393, "x": 142.99096276738686, "index": 5, "weight": 1, "px": 143.0997260146663, "group": 1, "name": "F", "count": 1}, "source": {"py": 141.2212767674666, "y": 141.27620239855642, "x": 171.0878962019167, "index": 3, "weight": 5, "px": 171.08507976631708, "group": 1, "name": "D", "count": 5}, "value": 1, "index": 7, "distance": 1}, {"target": {"py": 181.22652487706597, "y": 181.25464708439398, "x": 169.96110934707184, "index": 6, "weight": 3, "px": 169.95060689829097, "group": 1, "name": "G", "count": 3}, "source": {"py": 141.2212767674666, "y": 141.27620239855642, "x": 171.0878962019167, "index": 3, "weight": 5, "px": 171.08507976631708, "group": 1, "name": "D", "count": 5}, "value": 1, "index": 8, "distance": 1}, {"target": {"py": 204.599396603439, "y": 204.67371117661204, "x": 154.91175571918973, "index": 7, "weight": 2, "px": 155.00333042533964, "group": 1, "name": "H", "count": 2}, "source": {"py": 181.22652487706597, "y": 181.25464708439398, "x": 169.96110934707184, "index": 6, "weight": 3, "px": 169.95060689829097, "group": 1, "name": "G", "count": 3}, "value": 1, "index": 9, "distance": 1}, {"target": {"py": 210.93459130975953, "y": 211.01479296540714, "x": 175.01346154480248, "index": 8, "weight": 3, "px": 174.97638024734576, "group": 1, "name": "I", "count": 3}, "source": {"py": 181.22652487706597, "y": 181.25464708439398, "x": 169.96110934707184, "index": 6, "weight": 3, "px": 169.95060689829097, "group": 1, "name": "G", "count": 3}, "value": 1, "index": 10, "distance": 1}, {"target": {"py": 210.93459130975953, "y": 211.01479296540714, "x": 175.01346154480248, "index": 8, "weight": 3, "px": 174.97638024734576, "group": 1, "name": "I", "count": 3}, "source": {"py": 204.599396603439, "y": 204.67371117661204, "x": 154.91175571918973, "index": 7, "weight": 2, "px": 155.00333042533964, "group": 1, "name": "H", "count": 2}, "value": 1, "index": 11, "distance": 1}, {"target": {"py": 236.44674748831156, "y": 236.57130574504052, "x": 179.76585902861456, "index": 9, "weight": 1, "px": 179.74721897630533, "group": 1, "name": "J", "count": 1}, "source": {"py": 210.93459130975953, "y": 211.01479296540714, "x": 175.01346154480248, "index": 8, "weight": 3, "px": 174.97638024734576, "group": 1, "name": "I", "count": 3}, "value": 1, "index": 12, "distance": 1}, {"target": {"py": 98.03651552415523, "y": 97.94895743949343, "x": 135.59121731309256, "index": 10, "weight": 1, "px": 135.68754514283185, "group": 1, "name": "K", "count": 1}, "source": {"py": 115.8417026577427, "y": 115.7786456437307, "x": 161.75725315340017, "index": 2, "weight": 4, "px": 161.8305553067968, "group": 1, "name": "C", "count": 4}, "value": 1, "index": 13, "distance": 1}], "nodes": [{"py": 86.04501386415056, "y": 85.9439055032527, "x": 197.13123453913713, "index": 0, "weight": 1, "px": 197.05283896299326, "group": 1, "name": "A", "count": 1}, {"py": 109.98091501061916, "y": 109.87644784420979, "x": 181.2500954500423, "index": 1, "weight": 4, "px": 181.1961762476734, "group": 1, "name": "B", "count": 4}, {"py": 115.8417026577427, "y": 115.7786456437307, "x": 161.75725315340017, "index": 2, "weight": 4, "px": 161.8305553067968, "group": 1, "name": "C", "count": 4}, {"py": 141.2212767674666, "y": 141.27620239855642, "x": 171.0878962019167, "index": 3, "weight": 5, "px": 171.08507976631708, "group": 1, "name": "D", "count": 5}, {"py": 126.31898383120767, "y": 126.33450915777004, "x": 184.7865793573908, "index": 4, "weight": 3, "px": 184.6837066614665, "group": 1, "name": "E", "count": 3}, {"py": 148.0720222931251, "y": 148.09637522456393, "x": 142.99096276738686, "index": 5, "weight": 1, "px": 143.0997260146663, "group": 1, "name": "F", "count": 1}, {"py": 181.22652487706597, "y": 181.25464708439398, "x": 169.96110934707184, "index": 6, "weight": 3, "px": 169.95060689829097, "group": 1, "name": "G", "count": 3}, {"py": 204.599396603439, "y": 204.67371117661204, "x": 154.91175571918973, "index": 7, "weight": 2, "px": 155.00333042533964, "group": 1, "name": "H", "count": 2}, {"py": 210.93459130975953, "y": 211.01479296540714, "x": 175.01346154480248, "index": 8, "weight": 3, "px": 174.97638024734576, "group": 1, "name": "I", "count": 3}, {"py": 236.44674748831156, "y": 236.57130574504052, "x": 179.76585902861456, "index": 9, "weight": 1, "px": 179.74721897630533, "group": 1, "name": "J", "count": 1}, {"py": 98.03651552415523, "y": 97.94895743949343, "x": 135.59121731309256, "index": 10, "weight": 1, "px": 135.68754514283185, "group": 1, "name": "K", "count": 1}]}, "matching": {"useridx": [2, 3, 4, 3], "userorder": [3, 1, 2], "usermode": "cm", "currentmode": "cm", "currentidx": [2, 3, 4, 3], "currentorder": [3, 1, 2]}}