{"usercount":0,"connectivity":[{"usermode":"nl","currentgraph":[1,2,3],"currentmode":"nl","usergraph":[1,2,3]},{"usermode":"gt","currentgraph":[2,3,1],"currentmode":"gt","usergraph":[2,3,1]},{"usermode":"mx","currentgraph":[3,1,2],"currentmode":"mx","usergraph":[3,1,2]}],"matching":{"usermode":"gt","useridx":[0,1],"currentmode":"gt","currentidx":[0,1],"userorder":[1,2,3],"currentorder":[1,2,3]},"dense":{"usermode":"nl","useridx":[0,1,2],"currentmode":"nl","currentidx":[0,1,2],"userorder":[0,1],"currentorder":[0,1]}}