{"usercount": 3, "matching": {"currentmode": "mx", "userorder": [1, 2, 3], "useridx": [0, 1], "currentorder": [2, 3, 1], "currentidx": [1, 1], "usermode": "gt"}, "connectivity": [{"currentmode": "nl", "usermode": "nl", "currentgraph": [1, 2, 3], "usergraph": [1, 2, 3]}, {"currentmode": "gt", "usermode": "gt", "currentgraph": [2, 3, 1], "usergraph": [2, 3, 1]}, {"currentmode": "mx", "usermode": "mx", "currentgraph": [3, 1, 2], "usergraph": [3, 1, 2]}], "dense": {"currentmode": "nl", "userorder": [0, 1], "useridx": [0, 1, 2], "currentorder": [0, 1], "currentidx": [0, 1, 2], "usermode": "nl"}}